{
  "askcliStatesVersion": "2020-03-31",
  "profiles": {
    "default": {
      "skillId": "amzn1.ask.skill.8f5a6f1e-4755-4b36-9a5e-efecc50f39b9",
      "skillInfrastructure": {
        "@ask-cli/lambda-deployer": {
          "deployState": {
            "default": {
              "lambda": {
                "arn": "arn:aws:lambda:us-east-1:068726337588:function:ask-gymbuddy-default-default-1693075095728",
                "lastModified": "2023-08-26T20:55:20.000+0000",
                "revisionId": "69ca11be-005d-4057-b81b-701dc2bbe4a5"
              },
              "iamRole": "arn:aws:iam::068726337588:role/ask-lambda-gymbuddy-1693075093430"
            }
          }
        }
      },
      "skillMetadata": {
        "lastDeployHash": "7WRtQkgKttZ3IkRigCKqzEf1Dgg=",
        "lastDeployType": "interaction-model"
      },
      "code": {
        "default": {
          "lastDeployHash": "HTifRvWLmvQXreLQ5v4yusXC7YU="
        }
      }
    }
  }
}